lectioscraper/__init__.py
lectioscraper/getAbsence.py
lectioscraper/getAllHomework.py
lectioscraper/getAssignments.py
lectioscraper/getSchedule.py
lectioscraper/getTodaysSchedule.py
lectioscraper/getUnreadMessages.py
lectioscraper/lectioToCalendar.py
lectioscraper/lectioscraper.py
lectioscraper/quickstart.py
lectioscraper-0.0.6.6.dist-info/LICENSE
lectioscraper-0.0.6.6.dist-info/METADATA
lectioscraper-0.0.6.6.dist-info/WHEEL
lectioscraper-0.0.6.6.dist-info/top_level.txt
lectioscraper-0.0.6.6.dist-info/RECORD
