Metadata-Version: 2.1
Name: lectioscraper
Version: 0.0.6.6
Summary: A simple python package to scrape useful data from Lectio.dk
Home-page: https://github.com/Tovborg/LectioScraper
Author: Tovborg (Emil Tovborg-Jensen)
Author-email: <emil@tovborg-jensen.dk>
License: GNU General Public License v3.0
Download-URL: https://pypi.org/project/lectioscraper/
Keywords: python,Lectio,Scraping,webscraping
Platform: UNKNOWN
Requires-Dist: beautifulsoup4
Requires-Dist: requests
Requires-Dist: lxml
Requires-Dist: pytz
